baichuan/__init__.py
baichuan-0.0.1.dist-info/LICENSE
baichuan-0.0.1.dist-info/METADATA
baichuan-0.0.1.dist-info/WHEEL
baichuan-0.0.1.dist-info/RECORD
